{"authority_source":"spiffe://helm/authority/approvers","authority_version":"authority-v1","domain":"HELM/ApprovalAuthoritySnapshot/v1","keys":[{"actions":["install"],"audiences":["packs.lifecycle"],"credential_id":"credential-a","device_id":"device-a","enabled":true,"key_id":"key-a","not_after":"2026-07-15T13:15:00Z","not_before":"2026-07-15T11:00:00Z","principal_id":"principal-a","public_key":"ed25519:8a88e3dd7409f195fd52db2d3cba5d72ca6709bf1d94121bf3748801b40f6f5c","roles":["pack-admin"],"tenant_id":"tenant-a","workspace_ids":["workspace-a"]},{"actions":["install"],"audiences":["packs.lifecycle"],"credential_id":"credential-b","device_id":"device-b","enabled":true,"key_id":"key-b","not_after":"2026-07-15T13:15:00Z","not_before":"2026-07-15T11:00:00Z","principal_id":"principal-b","public_key":"ed25519:8139770ea87d175f56a35466c34c7ecccb8d8a91b4ee37a25df60f5b8fc9b394","roles":["pack-admin"],"tenant_id":"tenant-a","workspace_ids":["workspace-a"]},{"actions":["install"],"audiences":["packs.lifecycle"],"credential_id":"credential-c","device_id":"device-c","enabled":true,"key_id":"key-c","not_after":"2026-07-15T13:15:00Z","not_before":"2026-07-15T11:00:00Z","principal_id":"principal-c","public_key":"ed25519:ed4928c628d1c2c6eae90338905995612959273a5c63f93636c14614ac8737d1","roles":["pack-admin"],"tenant_id":"tenant-a","workspace_ids":["workspace-a"]}]}
